AUTHORS
ChangeLog
LICENSE
README.md
setup.cfg
setup.py
Webster/webster.py
Webster.egg-info/PKG-INFO
Webster.egg-info/SOURCES.txt
Webster.egg-info/dependency_links.txt
Webster.egg-info/not-zip-safe
Webster.egg-info/top_level.txt
webster/webster.py