Metadata-Version: 1.1
Name: Webster
Version: 0.5.1
Summary: Webster is a self validating dict object for python.
Home-page: http://www.davidlenwell.com/
Author: David Lenwell
Author-email: dlenwell@gmail.com
License: UNKNOWN
Platform: UNKNOWN
Classifier: Environment :: Console
Classifier: Intended Audience :: Developers
Classifier: Intended Audience :: Information Technology
Classifier: License :: OSI Approved :: Apache Software License
Classifier: Operating System :: POSIX :: Linux
Classifier: Programming Language :: Python
Classifier: Programming Language :: Python :: 2
Classifier: Programming Language :: Python :: 2.7
Classifier: Programming Language :: Python :: 3.3
